smq/___\client_manager.py
smq/____client_factory.py
smq/___client_agent.py
smq/___client_factory.py
smq/___client_manager.py
smq/__init__.py
smq/client_factory.py
smq/client_manager.py
smq/register_manager.py
smq/smq_server.py
smq/brokers/___simple_topic_agent.py
smq/brokers/___unique_key_topic_agent.py
smq/brokers/__init__.py
smq/brokers/simple_queue.py
smq/brokers/simple_topic.py
smq/brokers/simple_topic_agent.py
smq/brokers/unique_key_queue.py
smq/brokers/unique_key_topic.py
smq/brokers/unique_key_topic_agent.py
smq/clients/___simple_agent_client.py
smq/clients/___simple_topic_agent.py
smq/clients/___unique_key_agent_client.py
smq/clients/___unique_key_topic_agent.py
smq/clients/__init__.py
smq/clients/simple_agent_client.py
smq/clients/simple_client.py
smq/clients/simple_topic_agent.py
smq/clients/unique_key_agent_client.py
smq/clients/unique_key_client.py
smq/clients/unique_key_topic_agent.py
smq/common/__init__.py
smq/common/msg.py
smq/common/protocol.py
smq/common/tools.py
smq-0.0.32.dist-info/LICENSE
smq-0.0.32.dist-info/METADATA
smq-0.0.32.dist-info/WHEEL
smq-0.0.32.dist-info/top_level.txt
smq-0.0.32.dist-info/RECORD
